sequana_pipelines/denovo/__init__.py
sequana_pipelines/denovo/config.yaml
sequana_pipelines/denovo/dag.png
sequana_pipelines/denovo/denovo.rules
sequana_pipelines/denovo/main.py
sequana_pipelines/denovo/multiqc_config.yaml
sequana_pipelines/denovo/schema.yaml
sequana_pipelines/denovo/tools.txt
sequana_denovo-0.10.0.dist-info/LICENSE
sequana_denovo-0.10.0.dist-info/METADATA
sequana_denovo-0.10.0.dist-info/WHEEL
sequana_denovo-0.10.0.dist-info/entry_points.txt
sequana_denovo-0.10.0.dist-info/RECORD
